reprounzip_vistrails-1.2-py3.10-nspkg.pth
reprounzip/plugins/vistrails.py
reprounzip_vistrails-1.2.dist-info/LICENSE.txt
reprounzip_vistrails-1.2.dist-info/METADATA
reprounzip_vistrails-1.2.dist-info/WHEEL
reprounzip_vistrails-1.2.dist-info/entry_points.txt
reprounzip_vistrails-1.2.dist-info/namespace_packages.txt
reprounzip_vistrails-1.2.dist-info/top_level.txt
reprounzip_vistrails-1.2.dist-info/RECORD
