Metadata-Version: 2.1
Name: reprounzip-vistrails
Version: 1.2
Summary: Integrates the ReproZip unpacker with the VisTrails workflow management system
Home-page: https://www.reprozip.org/
Author: Remi Rampin, Fernando Chirigati, Dennis Shasha, Juliana Freire
Author-email: reprozip@nyu.edu
Maintainer: Remi Rampin
Maintainer-email: remi@rampin.org
License: BSD-3-Clause
Project-URL: Documentation, https://docs.reprozip.org/
Project-URL: Examples, https://examples.reprozip.org/
Project-URL: Source, https://github.com/VIDA-NYU/reprozip
Project-URL: Bug Tracker, https://github.com/VIDA-NYU/reprozip/issues
Project-URL: Chat, https://riot.im/app/#/room/#reprozip:matrix.org
Project-URL: Changelog, https://github.com/VIDA-NYU/reprozip/blob/1.x/CHANGELOG.md
Keywords: reprozip,reprounzip,reproducibility,provenance,vida,nyu,vistrails
Classifier: Development Status :: 4 - Beta
Classifier: Intended Audience :: Science/Research
Classifier: License :: OSI Approved :: BSD License
Classifier: Programming Language :: Python :: 2.7
Classifier: Programming Language :: Python :: 3
Classifier: Topic :: Scientific/Engineering
Classifier: Topic :: System :: Archiving
License-File: LICENSE.txt
Requires-Dist: reprounzip (>=1.0.0)
Requires-Dist: rpaths (>=0.8)
